counterer/counterer.py
counterer-0.0.2.dist-info/METADATA
counterer-0.0.2.dist-info/WHEEL
counterer-0.0.2.dist-info/entry_points.txt
counterer-0.0.2.dist-info/top_level.txt
counterer-0.0.2.dist-info/RECORD
