Metadata-Version: 2.1
Name: counterer
Version: 0.0.2
Summary: Simple counter
Home-page: https://github.com/meain/counterer
Author: Abin Simon
Author-email: abinsimon10@gmail.com
License: UNKNOWN
Keywords: counter,python
Platform: UNKNOWN
Classifier: Programming Language :: Python :: 3
Classifier: License :: OSI Approved :: MIT License
Classifier: Operating System :: OS Independent
